README.md
setup.py
cubi/__init__.py
cubi/engine.py
cubi/logger.py
cubi/params.py
cubi/proxy.py
cubi/utils.py
cubi.egg-info/PKG-INFO
cubi.egg-info/SOURCES.txt
cubi.egg-info/dependency_links.txt
cubi.egg-info/requires.txt
cubi.egg-info/top_level.txt