Metadata-Version: 1.0
Name: cubi
Version: 0.1.1
Summary: python implementation for Cube RPC protocol
Home-page: https://github.com/liaohuqiu/cube-rpc-python
Author: http://www.liaohuqiu.net
Author-email: liaohuqiu@gmail.com
License: MIT License
Keywords: cube,cubi,cube-rpc
Platform: any
